{
  "project_info": {
    "project_number": "1042053211991",
    "project_id": "study-squad-3d4fa",
    "storage_bucket": "study-squad-3d4fa.appspot.com"
  },
  "client": [
    {
      "client_info": {
        "mobilesdk_app_id": "1:1042053211991:android:df457f5ac5f6c03d474012",
        "android_client_info": {
          "package_name": "agu.devs.study_squad"
        }
      },
      "oauth_client": [],
      "api_key": [
        {
          "current_key": "AIzaSyB6-gfurm_BqYMU99JwJoZAQcFhYOdJMRU"
        }
      ],
      "services": {
        "appinvite_service": {
          "other_platform_oauth_client": []
        }
      }
    }
  ],
  "configuration_version": "1"
}